chora_mcp_gateway/__init__.py
chora_mcp_gateway/health_checker.py
chora_mcp_gateway/main.py
chora_mcp_gateway/models.py
chora_mcp_gateway/registry_poller.py
chora_mcp_gateway/router.py
chora_mcp_gateway/server.py
chora_mcp_gateway-0.1.0.dist-info/METADATA
chora_mcp_gateway-0.1.0.dist-info/WHEEL
chora_mcp_gateway-0.1.0.dist-info/RECORD
